sms_over_smtp/__init__.py
sms_over_smtp/__main__.py
sms_over_smtp/constants.py
sms_over_smtp/errors.py
sms_over_smtp/main.py
sms_over_smtp/provider.py
sms_over_smtp/util.py
sms_over_smtp/commands/__init__.py
sms_over_smtp/commands/list_providers.py
sms_over_smtp/commands/search_providers.py
sms_over_smtp-0.2.0.dist-info/LICENSE
sms_over_smtp-0.2.0.dist-info/METADATA
sms_over_smtp-0.2.0.dist-info/WHEEL
sms_over_smtp-0.2.0.dist-info/entry_points.txt
sms_over_smtp-0.2.0.dist-info/top_level.txt
sms_over_smtp-0.2.0.dist-info/RECORD
