Metadata-Version: 2.1
Name: sms-over-smtp
Version: 0.2.0
Summary: A package for sending SMS and MMS messages over SMTP.
Home-page: https://github.com/jordanshatford/sms-over-smtp
Author: Jordan Shatford
Author-email: jordanshatford@live.com
License: MIT
Classifier: License :: OSI Approved :: MIT License
Classifier: Programming Language :: Python :: 3
Classifier: Programming Language :: Python :: 3 :: Only
Classifier: Programming Language :: Python :: Implementation :: CPython
Classifier: Programming Language :: Python :: Implementation :: PyPy
Requires-Python: >=3.7
License-File: LICENSE
